evodev/__init__.py
evodev/web_projects.py
evodev-0.1.16.dist-info/licenses/LICENSE
evodev-0.1.16.dist-info/METADATA
evodev-0.1.16.dist-info/WHEEL
evodev-0.1.16.dist-info/top_level.txt
evodev-0.1.16.dist-info/RECORD
