Metadata-Version: 2.4
Name: evodev
Version: 0.1.16
Summary: Automated Development Environment
Author: Tom Sapletta
License-Expression: Apache-2.0
Project-URL: Documentation, https://github.com/tom-sapletta-com/evodev/blob/main/README.md
Project-URL: Changelog, https://github.com/tom-sapletta-com/evodev/blob/main/CHANGELOG.md
Project-URL: MonitoringSystemDocs, https://github.com/tom-sapletta-com/evodev/blob/main/docs/monitoring-system.md
Project-URL: Repository, https://github.com/tom-sapletta-com/evodev.git
Requires-Python: >=3.8
License-File: LICENSE
Dynamic: license-file
Dynamic: requires-python
